{"tt1704573": {"userMeter": "72", "userreviews": "41152", "Gross": "10050396", "url": "http://www.imdb.com/title/tt1704573/?ref_=nv_sr_1", "releasedate": "22 Jun 2012", "tomatoMeter": "89", "title": "Bernie", "contentrating": "PG-13", "metascore": "75", "popularity": "3082", "Screens": "3", "imdb_rating": "6.8", "rotten_url": "https://www.rottentomatoes.com/m/bernie_2011/", "tomatoRating": "7.5", "userrating": "3.7", "year": "2011", "Genre": ["Comedy", "Crime", "Drama"], "budget": "5460277", "runtime": "104 min", "OpeningWeekend": "93703"}, "tt1596343": {"userMeter": "83", "userreviews": "138423", "Gross": "229154384", "url": "http://www.imdb.com/title/tt1596343/?ref_=nv_sr_1", "releasedate": "29 Apr 2011", "tomatoMeter": "77", "title": "Fast Five", "contentrating": "PG-13", "metascore": "67", "popularity": "1561", "Screens": "3644", "imdb_rating": "7.3", "rotten_url": "https://www.rottentomatoes.com/m/fast_five/", "tomatoRating": "6.4", "userrating": "4.0", "year": "2011", "Genre": ["Action", "Crime", "Thriller"], "budget": "136506935", "runtime": "131 min", "OpeningWeekend": "94133834"}, "tt1622547": {"userMeter": "40", "userreviews": "46736", "Gross": "40464940", "url": "http://www.imdb.com/title/tt1622547/?ref_=nv_sr_1", "releasedate": "12 Aug 2011", "tomatoMeter": "44", "title": "30 Minutes or Less", "contentrating": "R", "metascore": "49", "popularity": "4379", "Screens": "2888", "imdb_rating": "6.1", "rotten_url": "https://www.rottentomatoes.com/m/30_minutes_or_less/", "tomatoRating": "5.4", "userrating": "3.0", "year": "2011", "Genre": ["Action", "Comedy", "Crime"], "budget": "30577553", "runtime": "83 min", "OpeningWeekend": "14557228"}, "tt1464174": {"userMeter": "58", "userreviews": "132009", "Gross": "41401872", "url": "http://www.imdb.com/title/tt1464174/?ref_=nv_sr_1", "releasedate": "18 Feb 2011", "tomatoMeter": "5", "title": "Big Mommas: Like Father, Like Son", "contentrating": "PG-13", "metascore": "22", "popularity": "empty", "Screens": "2821", "imdb_rating": "4.4", "rotten_url": "https://www.rottentomatoes.com/m/big_mommas_like_father_like_son_2011/", "tomatoRating": "2.7", "userrating": "3.5", "year": "2011", "Genre": ["Action", "Comedy", "Crime"], "budget": "34945775", "runtime": "107 min", "OpeningWeekend": "20749054"}, "tt1515091": {"userMeter": "77", "userreviews": "167532", "Gross": "203956932", "url": "http://www.imdb.com/title/tt1515091/?ref_=nv_sr_1", "releasedate": "16 Dec 2011", "tomatoMeter": "60", "title": "Sherlock Holmes: A Game of Shadows", "contentrating": "PG-13", "metascore": "48", "popularity": "1686", "Screens": "3703", "imdb_rating": "7.5", "rotten_url": "https://www.rottentomatoes.com/m/sherlock_holmes_a_game_of_shadows/", "tomatoRating": "6", "userrating": "3.9", "year": "2011", "Genre": ["Action", "Adventure", "Crime"], "budget": "136506935", "runtime": "129 min", "OpeningWeekend": "43285889"}, "tt1934231": {"userMeter": "82", "userreviews": "4371", "title": "Delhi Belly", "url": "http://www.imdb.com/title/tt1934231/?ref_=nv_sr_1", "releasedate": "01 Jul 2011", "Gross": "1672763", "popularity": "empty", "contentrating": "N/A", "metascore": "66", "budget": "empty", "Screens": "empty", "imdb_rating": "7.6", "rotten_url": "https://www.rottentomatoes.com/m/delhi_belly_2011/", "tomatoRating": "6.6", "year": "2011", "Genre": ["Comedy", "Crime", "Drama"], "userrating": "3.9", "runtime": "103 min", "tomatoMeter": "92", "OpeningWeekend": "empty"}, "tt1657507": {"userMeter": "67", "userreviews": "161678", "Gross": "40041146", "url": "http://www.imdb.com/title/tt1657507/?ref_=nv_sr_1", "releasedate": "26 Aug 2011", "tomatoMeter": "27", "title": "Colombiana", "contentrating": "PG-13", "metascore": "45", "popularity": "3496", "Screens": "2614", "imdb_rating": "6.4", "rotten_url": "https://www.rottentomatoes.com/m/colombiana/", "tomatoRating": "4.8", "userrating": "3.8", "year": "2011", "Genre": ["Action", "Crime", "Drama"], "budget": "43682219", "runtime": "108 min", "OpeningWeekend": "11366305"}, "tt1614989": {"userMeter": "85", "userreviews": "24496", "Gross": "1306919", "url": "http://www.imdb.com/title/tt1614989/?ref_=nv_sr_1", "releasedate": "26 Aug 2011", "tomatoMeter": "92", "title": "Headhunters", "contentrating": "R", "metascore": "72", "popularity": "3506", "Screens": "4", "imdb_rating": "7.6", "rotten_url": "https://www.rottentomatoes.com/m/headhunters/", "tomatoRating": "7.6", "userrating": "4.0", "year": "2011", "Genre": ["Crime", "Drama", "Thriller"], "budget": "3970713", "runtime": "100 min", "OpeningWeekend": "46972"}, "tt0472399": {"userMeter": "51", "userreviews": "57321", "Gross": "31802291", "url": "http://www.imdb.com/title/tt0472399/?ref_=nv_sr_1", "releasedate": "28 Jan 2011", "tomatoMeter": "53", "title": "The Mechanic", "contentrating": "R", "metascore": "49", "popularity": "237", "Screens": "2703", "imdb_rating": "6.6", "rotten_url": "https://www.rottentomatoes.com/m/mechanic/", "tomatoRating": "5.6", "userrating": "3.3", "year": "2011", "Genre": ["Action", "Crime", "Thriller"], "budget": "43682219", "runtime": "93 min", "OpeningWeekend": "12473464"}, "tt1540133": {"userMeter": "81", "userreviews": "25359", "Gross": "5853170", "url": "http://www.imdb.com/title/tt1540133/?ref_=nv_sr_1", "releasedate": "07 Jul 2011", "tomatoMeter": "94", "title": "The Guard", "contentrating": "R", "metascore": "78", "popularity": "4883", "Screens": "4", "imdb_rating": "7.3", "rotten_url": "https://www.rottentomatoes.com/m/the_guard_2011/", "tomatoRating": "7.6", "userrating": "3.9", "year": "2011", "Genre": ["Comedy", "Crime", "Thriller"], "budget": "6552332", "runtime": "96 min", "OpeningWeekend": "83906"}, "tt1726669": {"userMeter": "61", "userreviews": "79826", "Gross": "240560", "url": "http://www.imdb.com/title/tt1726669/?ref_=nv_sr_1", "releasedate": "29 Jun 2012", "tomatoMeter": "78", "title": "Killer Joe", "contentrating": "R", "metascore": "62", "popularity": "3270", "Screens": "3", "imdb_rating": "6.7", "rotten_url": "https://www.rottentomatoes.com/m/killer_joe/", "tomatoRating": "6.9", "userrating": "3.4", "year": "2011", "Genre": ["Crime", "Drama", "Romance"], "budget": "12012610", "runtime": "102 min", "OpeningWeekend": "41349"}, "tt1499658": {"userMeter": "70", "userreviews": "105855", "Gross": "128358628", "url": "http://www.imdb.com/title/tt1499658/?ref_=nv_sr_1", "releasedate": "08 Jul 2011", "tomatoMeter": "68", "title": "Horrible Bosses", "contentrating": "R", "metascore": "57", "popularity": "1558", "Screens": "3040", "imdb_rating": "6.9", "rotten_url": "https://www.rottentomatoes.com/m/horrible_bosses/", "tomatoRating": "6.2", "userrating": "3.6", "year": "2011", "Genre": ["Comedy", "Crime"], "budget": "38221941", "runtime": "98 min", "OpeningWeekend": "30907534"}, "tt1899353": {"userMeter": "87", "userreviews": "51465", "Gross": "4483022", "url": "http://www.imdb.com/title/tt1899353/?ref_=nv_sr_1", "releasedate": "13 Apr 2012", "tomatoMeter": "85", "title": "The Raid: Redemption", "contentrating": "R", "metascore": "73", "popularity": "1714", "Screens": "14", "imdb_rating": "7.6", "rotten_url": "https://www.rottentomatoes.com/m/the_raid_redemption/", "tomatoRating": "7.5", "userrating": "4.1", "year": "2011", "Genre": ["Action", "Crime", "Thriller"], "budget": "1201261", "runtime": "101 min", "OpeningWeekend": "233465"}, "tt1285241": {"userMeter": "72", "userreviews": "4510", "Gross": "4019098", "url": "http://www.imdb.com/title/tt1285241/?ref_=nv_sr_1", "releasedate": "23 Dec 2011", "tomatoMeter": "73", "title": "Don 2", "contentrating": "NOT RATED", "metascore": "49", "popularity": "empty", "Screens": "empty", "imdb_rating": "7.1", "rotten_url": "https://www.rottentomatoes.com/m/don_2/", "tomatoRating": "6.8", "userrating": "3.7", "year": "2011", "Genre": ["Action", "Crime", "Thriller"], "budget": "18237326", "runtime": "148 min", "OpeningWeekend": "2839344"}, "tt1189340": {"userMeter": "82", "userreviews": "67967", "Gross": "63319439", "url": "http://www.imdb.com/title/tt1189340/?ref_=nv_sr_1", "releasedate": "18 Mar 2011", "tomatoMeter": "83", "title": "The Lincoln Lawyer", "contentrating": "R", "metascore": "63", "popularity": "1835", "Screens": "2707", "imdb_rating": "7.3", "rotten_url": "https://www.rottentomatoes.com/m/lincoln_lawyer/", "tomatoRating": "6.6", "userrating": "3.8", "year": "2011", "Genre": ["Crime", "Drama", "Thriller"], "budget": "43682219", "runtime": "118 min", "OpeningWeekend": "14422179"}, "tt1448755": {"userMeter": "42", "userreviews": "32262", "Gross": "27403611", "url": "http://www.imdb.com/title/tt1448755/?ref_=nv_sr_1", "releasedate": "23 Sep 2011", "tomatoMeter": "25", "title": "Killer Elite", "contentrating": "R", "metascore": "44", "popularity": "2734", "Screens": "2986", "imdb_rating": "6.5", "rotten_url": "https://www.rottentomatoes.com/m/killer_elite_2011/", "tomatoRating": "4.7", "userrating": "3.1", "year": "2011", "Genre": ["Action", "Crime", "Thriller"], "budget": "38221941", "runtime": "116 min", "OpeningWeekend": "10156116"}, "tt1616195": {"userMeter": "44", "userreviews": "39665", "Gross": "40739075", "url": "http://www.imdb.com/title/tt1616195/?ref_=nv_sr_1", "releasedate": "11 Nov 2011", "tomatoMeter": "43", "title": "J. Edgar", "contentrating": "R", "metascore": "59", "popularity": "1946", "Screens": "1910", "imdb_rating": "6.6", "rotten_url": "https://www.rottentomatoes.com/m/j_edgar/", "tomatoRating": "5.7", "userrating": "3.1", "year": "2011", "Genre": ["Biography", "Crime", "Drama"], "budget": "38221941", "runtime": "137 min", "OpeningWeekend": "12249940"}, "tt1416801": {"userMeter": "67", "userreviews": "9299", "Gross": "2706283", "url": "http://www.imdb.com/title/tt1416801/?ref_=nv_sr_1", "releasedate": "11 May 2012", "tomatoMeter": "63", "title": "Kill the Irishman", "contentrating": "R", "metascore": "50", "popularity": "empty", "Screens": "5", "imdb_rating": "7.2", "rotten_url": "https://www.rottentomatoes.com/m/the-irishman/", "tomatoRating": "5.6", "userrating": "3.6", "year": "2011", "Genre": ["Biography", "Crime", "Drama"], "budget": "13104665", "runtime": "106 min", "OpeningWeekend": "158817"}, "tt1568346": {"userMeter": "86", "userreviews": "117504", "Gross": "111952934", "url": "http://www.imdb.com/title/tt1568346/?ref_=nv_sr_1", "releasedate": "21 Dec 2011", "tomatoMeter": "86", "title": "The Girl with the Dragon Tattoo", "contentrating": "R", "metascore": "71", "popularity": "288", "Screens": "2914", "imdb_rating": "7.8", "rotten_url": "https://www.rottentomatoes.com/m/the_girl_with_the_dragon_tattoo/", "tomatoRating": "7.6", "userrating": "4.1", "year": "2011", "Genre": ["Crime", "Drama", "Mystery"], "budget": "98284993", "runtime": "158 min", "OpeningWeekend": "13923707"}, "tt0990407": {"userMeter": "43", "userreviews": "116099", "Gross": "107873286", "url": "http://www.imdb.com/title/tt0990407/?ref_=nv_sr_1", "releasedate": "14 Jan 2011", "tomatoMeter": "43", "title": "The Green Hornet", "contentrating": "PG-13", "metascore": "39", "popularity": "2993", "Screens": "3584", "imdb_rating": "5.8", "rotten_url": "https://www.rottentomatoes.com/m/green_hornet/", "tomatoRating": "5.2", "userrating": "3.1", "year": "2011", "Genre": ["Action", "Comedy", "Crime"], "budget": "131046658", "runtime": "119 min", "OpeningWeekend": "36613208"}, "tt0780504": {"userMeter": "79", "userreviews": "115385", "Gross": "38288217", "url": "http://www.imdb.com/title/tt0780504/?ref_=nv_sr_1", "releasedate": "16 Sep 2011", "tomatoMeter": "92", "title": "Drive", "contentrating": "R", "metascore": "78", "popularity": "426", "Screens": "2886", "imdb_rating": "7.8", "rotten_url": "https://www.rottentomatoes.com/m/drive_2011/", "tomatoRating": "8.3", "userrating": "3.9", "year": "2011", "Genre": ["Crime", "Drama"], "budget": "16380832", "runtime": "100 min", "OpeningWeekend": "12384412"}, "tt0471042": {"userMeter": "48", "userreviews": "57169", "Gross": "85190325", "url": "http://www.imdb.com/title/tt0471042/?ref_=nv_sr_1", "releasedate": "04 Nov 2011", "tomatoMeter": "68", "title": "Tower Heist", "contentrating": "PG-13", "metascore": "59", "popularity": "3366", "Screens": "3367", "imdb_rating": "6.2", "rotten_url": "https://www.rottentomatoes.com/m/tower_heist/", "tomatoRating": "6.2", "userrating": "3.3", "year": "2011", "Genre": ["Action", "Comedy", "Crime"], "budget": "81904161", "runtime": "104 min", "OpeningWeekend": "26236840"}}