{"tt0187393": {"Screens": "3,061", "title": "The Patriot", "url": "http://www.imdb.com/title/tt0187393/?ref_=nv_sr_1", "Gross": "$113,330,342", "popularity": "875", "contentrating": "R", "metascore": "63", "budget": "$110,000,000", "releasedate": "28 Jun 2000", "imdb_rating": "7.1", "OpeningWeekend": "$22,413,710 (USA) ", "year": "2000", "Genre": ["Action", "Drama", "History"], "runtime": "165 min"}, "tt0195685": {"Screens": "2,848", "title": "Erin Brockovich", "url": "http://www.imdb.com/title/tt0195685/?ref_=nv_sr_1", "Gross": "$125,548,685", "popularity": "1,400", "contentrating": "R", "metascore": "73", "budget": "$52,000,000", "releasedate": "17 Mar 2000", "imdb_rating": "7.3", "OpeningWeekend": "$28,138,465 (USA) ", "year": "2000", "Genre": ["Biography", "Drama"], "runtime": "131 min"}, "tt0212346": {"Screens": "2,668", "title": "Miss Congeniality", "url": "http://www.imdb.com/title/tt0212346/?ref_=nv_sr_1", "Gross": "$106,807,667", "popularity": "2,408", "contentrating": "PG-13", "metascore": "43", "budget": "$45,000,000", "releasedate": "22 Dec 2000", "imdb_rating": "6.2", "OpeningWeekend": "$13,853,686 (USA) ", "year": "2000", "Genre": ["Action", "Comedy", "Crime"], "runtime": "109 min"}, "tt0210945": {"Screens": "1,865", "title": "Remember the Titans", "url": "http://www.imdb.com/title/tt0210945/?ref_=nv_sr_1", "Gross": "$115,648,585", "popularity": "1,014", "contentrating": "PG", "metascore": "48", "budget": "$30,000,000", "releasedate": "29 Sep 2000", "imdb_rating": "7.8", "OpeningWeekend": "$20,905,831 (USA) ", "year": "2000", "Genre": ["Biography", "Drama", "Sport"], "runtime": "113 min"}, "tt0144528": {"Screens": "3,242", "title": "Nutty Professor II: The Klumps", "url": "http://www.imdb.com/title/tt0144528/?ref_=nv_sr_1", "Gross": "$123,307,945", "popularity": "empty", "contentrating": "PG-13", "metascore": "38", "budget": "$84,000,000", "releasedate": "28 Jul 2000", "imdb_rating": "4.3", "OpeningWeekend": "$42,518,830 (USA) ", "year": "2000", "Genre": ["Comedy", "Romance", "Sci-Fi"], "runtime": "106 min"}, "tt0181865": {"Screens": "4", "title": "Traffic", "url": "http://www.imdb.com/title/tt0181865/?ref_=nv_sr_1", "Gross": "$124,107,476", "popularity": "1,873", "contentrating": "R", "metascore": "86", "budget": "$48,000,000", "releasedate": "05 Jan 2001", "imdb_rating": "7.6", "OpeningWeekend": "$184,725 (USA) ", "year": "2000", "Genre": ["Crime", "Drama", "Thriller"], "runtime": "147 min"}, "tt0130623": {"Screens": "3,257", "title": "Dinosaur", "url": "http://www.imdb.com/title/tt0130623/?ref_=nv_sr_1", "Gross": "$137,748,063", "popularity": "3,655", "contentrating": "PG", "metascore": "56", "budget": "$127,500,000", "releasedate": "19 May 2000", "imdb_rating": "6.5", "OpeningWeekend": "$38,854,851 (USA) ", "year": "2000", "Genre": ["Animation", "Adventure", "Family"], "runtime": "82 min"}, "tt0160127": {"Screens": "3,037", "title": "Charlie's Angels", "url": "http://www.imdb.com/title/tt0160127/?ref_=nv_sr_1", "Gross": "$125,305,545", "popularity": "1,956", "contentrating": "PG-13", "metascore": "52", "budget": "$93,000,000", "releasedate": "03 Nov 2000", "imdb_rating": "5.5", "OpeningWeekend": "$40,128,550 (USA) ", "year": "2000", "Genre": ["Action", "Adventure", "Comedy"], "runtime": "98 min"}, "tt0190332": {"Screens": "16", "title": "Crouching Tiger, Hidden Dragon", "url": "http://www.imdb.com/title/tt0190332/?ref_=nv_sr_1", "Gross": "$128,067,808", "popularity": "2,423", "contentrating": "PG-13", "metascore": "93", "budget": "$17,000,000", "releasedate": "12 Jan 2001", "imdb_rating": "7.9", "OpeningWeekend": "$663,205 (USA) ", "year": "2000", "Genre": ["Action", "Drama", "Romance"], "runtime": "120 min"}, "tt0208003": {"Screens": "2,802", "title": "Big Momma's House", "url": "http://www.imdb.com/title/tt0208003/?ref_=nv_sr_1", "Gross": "$117,559,438", "popularity": "empty", "contentrating": "PG-13", "metascore": "33", "budget": "$30,000,000", "releasedate": "02 Jun 2000", "imdb_rating": "5.1", "OpeningWeekend": "$25,661,041 (USA) ", "year": "2000", "Genre": ["Action", "Comedy", "Crime"], "runtime": "99 min"}}