{"tt1702443": {"Screens": "3,105", "title": "Justin Bieber: Never Say Never", "url": "http://www.imdb.com/title/tt1702443/?ref_=nv_sr_1", "Gross": "$73,000,942", "popularity": "empty", "contentrating": "G", "metascore": "52", "budget": "$13,000,000", "releasedate": "11 Feb 2011", "imdb_rating": "1.6", "OpeningWeekend": "$29,514,054 (USA) ", "year": "2011", "Genre": ["Documentary", "Music"], "runtime": "105 min"}, "tt0970179": {"Screens": "1,277", "title": "Hugo", "url": "http://www.imdb.com/title/tt0970179/?ref_=nv_sr_1", "Gross": "$73,864,507", "popularity": "722", "contentrating": "PG", "metascore": "83", "budget": "$170,000,000", "releasedate": "23 Nov 2011", "imdb_rating": "7.5", "OpeningWeekend": "$11,364,505 (USA) ", "year": "2011", "Genre": ["Adventure", "Drama", "Family"], "runtime": "126 min"}, "tt1389137": {"Screens": "3,117", "title": "We Bought a Zoo", "url": "http://www.imdb.com/title/tt1389137/?ref_=nv_sr_1", "Gross": "$75,621,915", "popularity": "1,557", "contentrating": "PG", "metascore": "58", "budget": "empty", "releasedate": "23 Dec 2011", "imdb_rating": "7.1", "OpeningWeekend": "$9,450,000 (USA) ", "year": "2011", "Genre": ["Comedy", "Drama", "Family"], "runtime": "124 min"}, "tt1210166": {"Screens": "2,993", "title": "Moneyball", "url": "http://www.imdb.com/title/tt1210166/?ref_=nv_sr_1", "Gross": "$75,605,492", "popularity": "1,593", "contentrating": "PG-13", "metascore": "87", "budget": "$50,000,000", "releasedate": "23 Sep 2011", "imdb_rating": "7.6", "OpeningWeekend": "$19,501,302 (USA) ", "year": "2011", "Genre": ["Biography", "Drama", "Sport"], "runtime": "133 min"}, "tt1564349": {"Screens": "3,507", "title": "Dolphin Tale", "url": "http://www.imdb.com/title/tt1564349/?ref_=nv_sr_1", "Gross": "$72,279,690", "popularity": "empty", "contentrating": "PG", "metascore": "64", "budget": "$37,000,000", "releasedate": "23 Sep 2011", "imdb_rating": "6.9", "OpeningWeekend": "$19,152,401 (USA) ", "year": "2011", "Genre": ["Drama", "Family"], "runtime": "113 min"}, "tt0983193": {"Screens": "", "title": "The Adventures of Tintin", "url": "http://www.imdb.com/title/tt0983193/?ref_=nv_sr_1", "Gross": "$77,564,037", "popularity": "2,676", "contentrating": "PG", "metascore": "68", "budget": "$135,000,000", "releasedate": "21 Dec 2011", "imdb_rating": "7.4", "OpeningWeekend": "$9,720,993 (USA) ", "year": "2011", "Genre": ["Animation", "Action", "Adventure"], "runtime": "107 min"}, "tt1598778": {"Screens": "3,222", "title": "Contagion", "url": "http://www.imdb.com/title/tt1598778/?ref_=nv_sr_1", "Gross": "$75,658,097", "popularity": "1,766", "contentrating": "PG-13", "metascore": "70", "budget": "$60,000,000", "releasedate": "09 Sep 2011", "imdb_rating": "6.6", "OpeningWeekend": "$22,403,596 (USA) ", "year": "2011", "Genre": ["Drama", "Thriller"], "runtime": "106 min"}, "tt1219289": {"Screens": "2,756", "title": "Limitless", "url": "http://www.imdb.com/title/tt1219289/?ref_=nv_sr_1", "Gross": "$79,249,455", "popularity": "780", "contentrating": "PG-13", "metascore": "59", "budget": "$27,000,000", "releasedate": "18 Mar 2011", "imdb_rating": "7.4", "OpeningWeekend": "$18,907,302 (USA) ", "year": "2011", "Genre": ["Mystery", "Sci-Fi", "Thriller"], "runtime": "105 min"}, "tt0810913": {"Screens": "3,438", "title": "Jack and Jill", "url": "http://www.imdb.com/title/tt0810913/?ref_=nv_sr_1", "Gross": "$74,158,157", "popularity": "1,928", "contentrating": "PG", "metascore": "23", "budget": "$79,000,000", "releasedate": "11 Nov 2011", "imdb_rating": "3.4", "OpeningWeekend": "$25,003,575 (USA) ", "year": "2011", "Genre": ["Comedy"], "runtime": "91 min"}, "tt0471042": {"Screens": "3,367", "title": "Tower Heist", "url": "http://www.imdb.com/title/tt0471042/?ref_=nv_sr_1", "Gross": "$78,009,155", "popularity": "3,366", "contentrating": "PG-13", "metascore": "59", "budget": "$75,000,000", "releasedate": "04 Nov 2011", "imdb_rating": "6.2", "OpeningWeekend": "$24,025,190 (USA) ", "year": "2011", "Genre": ["Action", "Comedy", "Crime"], "runtime": "104 min"}}