{"tt2626350": {"userMeter": "57%", "userreviews": "32,951", "Gross": "$14,897,580", "title": "Step Up All In", "url": "http://www.imdb.com/title/tt2626350/?ref_=nv_sr_1", "Screens": "2,072", "tomatoMeter": "43%", "popularity": "2,331", "contentrating": "PG-13", "metascore": "45", "budget": "$45,000,000", "releasedate": "08 Aug 2014", "imdb_rating": "6.0", "rotten_url": "https://www.rottentomatoes.com/m/step_up_all_in/", "tomatoRating": "5.1", "year": "2014", "Genre": ["Drama", "Music", "Romance"], "userrating": "3.5", "runtime": "112 min", "OpeningWeekend": "$6,575,000 (USA) "}, "tt3235888": {"userMeter": "65%", "userreviews": "40,437", "Gross": "$14,673,301", "title": "It Follows", "url": "http://www.imdb.com/title/tt3235888/?ref_=nv_sr_1", "Screens": "4", "tomatoMeter": "97%", "popularity": "437", "contentrating": "R", "metascore": "83", "budget": "$2,000,000", "releasedate": "27 Mar 2015", "imdb_rating": "6.9", "rotten_url": "https://www.rottentomatoes.com/m/it_follows/", "tomatoRating": "8.1", "year": "2014", "Genre": ["Horror", "Mystery"], "userrating": "3.5", "runtime": "100 min", "OpeningWeekend": "$160,089 (USA) "}, "tt2752758": {"userMeter": "21%", "userreviews": "21,113", "Gross": "$15,818,967", "title": "Devil's Due", "url": "http://www.imdb.com/title/tt2752758/?ref_=nv_sr_1", "Screens": "2,544", "tomatoMeter": "18%", "popularity": "empty", "contentrating": "R", "metascore": "34", "budget": "$7,000,000", "releasedate": "17 Jan 2014", "imdb_rating": "4.0", "rotten_url": "https://www.rottentomatoes.com/m/devils_due/", "tomatoRating": "4", "year": "2014", "Genre": ["Horror", "Mystery"], "userrating": "2.2", "runtime": "89 min", "OpeningWeekend": "$8,500,000 (USA) "}, "tt0458481": {"userMeter": "44%", "userreviews": "143,562", "Gross": "$13,757,804", "title": "Sin City: A Dame to Kill For", "url": "http://www.imdb.com/title/tt0458481/?ref_=nv_sr_1", "Screens": "2,894", "tomatoMeter": "43%", "popularity": "574", "contentrating": "R", "metascore": "46", "budget": "$65,000,000", "releasedate": "22 Aug 2014", "imdb_rating": "6.5", "rotten_url": "https://www.rottentomatoes.com/m/frank_millers_sin_city_a_dame_to_kill_for/", "tomatoRating": "5.4", "year": "2014", "Genre": ["Action", "Crime", "Thriller"], "userrating": "3.3", "runtime": "102 min", "OpeningWeekend": "$6,317,683 (USA) "}, "tt3695786": {"userMeter": "92%", "userreviews": "275,745", "Gross": "empty", "title": "America!", "url": "http://www.imdb.com/title/tt3695786/?ref_=nv_sr_1", "tomatoMeter": "89%", "popularity": "empty", "contentrating": "N/A", "metascore": "N/A", "budget": "empty", "releasedate": "26 Apr 2014", "imdb_rating": "5.7", "rotten_url": "https://www.rottentomatoes.com/m/captain_america_the_winter_soldier_2014/", "tomatoRating": "7.5", "year": "2014", "Genre": ["Short", "Comedy"], "userrating": "4.3", "runtime": "10 min"}, "tt2467046": {"userMeter": "40%", "userreviews": "20,275", "Gross": "$6,300,147", "title": "Left Behind", "url": "http://www.imdb.com/title/tt2467046/?ref_=nv_sr_1", "Screens": "1,825", "tomatoMeter": "2%", "popularity": "2,448", "contentrating": "PG-13", "metascore": "12", "budget": "$16,000,000", "releasedate": "03 Oct 2014", "imdb_rating": "3.1", "rotten_url": "https://www.rottentomatoes.com/m/left_behind_2014/", "tomatoRating": "2.1", "year": "2014", "Genre": ["Action", "Drama", "Fantasy"], "userrating": "2.7", "runtime": "110 min", "OpeningWeekend": "$6,300,147 (USA) "}, "tt1126590": {"userMeter": "69%", "userreviews": "31,559", "Gross": "$14,479,776", "title": "Big Eyes", "url": "http://www.imdb.com/title/tt1126590/?ref_=nv_sr_1", "Screens": "1,307", "tomatoMeter": "72%", "popularity": "1,309", "contentrating": "PG-13", "metascore": "62", "budget": "$10,000,000", "releasedate": "25 Dec 2014", "imdb_rating": "7.0", "rotten_url": "https://www.rottentomatoes.com/m/big_eyes/", "tomatoRating": "6.6", "year": "2014", "Genre": ["Biography", "Crime", "Drama"], "userrating": "3.6", "runtime": "106 min", "OpeningWeekend": "$3,001,738 (USA) "}, "tt3125324": {"userMeter": "75%", "userreviews": "19,056", "Gross": "$14,612,840", "title": "Beyond the Lights", "url": "http://www.imdb.com/title/tt3125324/?ref_=nv_sr_1", "tomatoMeter": "82%", "popularity": "2,893", "contentrating": "PG-13", "metascore": "73", "budget": "$7,000,000", "releasedate": "14 Nov 2014", "imdb_rating": "6.9", "rotten_url": "https://www.rottentomatoes.com/m/beyond_the_lights/", "tomatoRating": "6.8", "year": "2014", "Genre": ["Drama", "Music"], "userrating": "3.9", "runtime": "116 min"}, "tt2465140": {"userMeter": "59%", "userreviews": "26,765", "Gross": "$15,986,272", "title": "The Single Moms Club", "url": "http://www.imdb.com/title/tt2465140/?ref_=nv_sr_1", "Screens": "1,896", "tomatoMeter": "19%", "popularity": "4,203", "contentrating": "PG-13", "metascore": "31", "budget": "$8,000,000", "releasedate": "14 Mar 2014", "imdb_rating": "5.2", "rotten_url": "https://www.rottentomatoes.com/m/the_single_moms_club/", "tomatoRating": "4.4", "year": "2014", "Genre": ["Comedy", "Drama"], "userrating": "3.5", "runtime": "111 min", "OpeningWeekend": "$8,075,111 (USA) "}, "tt2465146": {"userMeter": "40%", "userreviews": "10,975", "Gross": "$15,155,772", "title": "And So It Goes", "url": "http://www.imdb.com/title/tt2465146/?ref_=nv_sr_1", "Screens": "1,762", "tomatoMeter": "19%", "popularity": "4,304", "contentrating": "PG-13", "metascore": "38", "budget": "$18,000,000", "releasedate": "25 Jul 2014", "imdb_rating": "5.7", "rotten_url": "https://www.rottentomatoes.com/m/and_so_it_goes/", "tomatoRating": "4.2", "year": "2014", "Genre": ["Comedy", "Drama", "Romance"], "userrating": "3.0", "runtime": "94 min", "OpeningWeekend": "$4,552,000 (USA) "}}