{"tt2473794": {"userMeter": "56%", "userreviews": "15,983", "Gross": "$3,958,500", "title": "Mr. Turner", "url": "http://www.imdb.com/title/tt2473794/?ref_=nv_sr_1", "tomatoMeter": "98%", "popularity": "4,785", "contentrating": "R", "metascore": "94", "budget": "\u00a38,200,000", "releasedate": "31 Oct 2014", "imdb_rating": "6.8", "rotten_url": "https://www.rottentomatoes.com/m/mr_turner/", "tomatoRating": "8.4", "year": "2014", "Genre": ["Biography", "Drama", "History"], "userrating": "3.3", "runtime": "150 min"}, "tt2771372": {"userMeter": "79%", "userreviews": "26,621", "Gross": "$3,319,109", "title": "Veronica Mars", "url": "http://www.imdb.com/title/tt2771372/?ref_=nv_sr_1", "Screens": "291", "tomatoMeter": "79%", "popularity": "2,111", "contentrating": "PG-13", "metascore": "62", "budget": "$6,000,000", "releasedate": "13 Mar 2014", "imdb_rating": "6.8", "rotten_url": "https://www.rottentomatoes.com/m/veronica_mars/", "tomatoRating": "6.7", "year": "2014", "Genre": ["Crime", "Drama", "Mystery"], "userrating": "4.1", "runtime": "107 min", "OpeningWeekend": "$1,988,351 (USA) "}, "tt2235108": {"userMeter": "63%", "userreviews": "21,879", "Gross": "$4,404,154", "title": "Dear White People", "url": "http://www.imdb.com/title/tt2235108/?ref_=nv_sr_1", "tomatoMeter": "91%", "popularity": "4,606", "contentrating": "R", "metascore": "79", "budget": "empty", "releasedate": "04 Dec 2014", "imdb_rating": "6.3", "rotten_url": "https://www.rottentomatoes.com/m/dear_white_people/", "tomatoRating": "7.5", "year": "2014", "Genre": ["Comedy", "Drama"], "userrating": "3.4", "runtime": "108 min"}, "tt3416742": {"userMeter": "86%", "userreviews": "24,363", "Gross": "$3,333,000", "title": "What We Do in the Shadows", "url": "http://www.imdb.com/title/tt3416742/?ref_=nv_sr_1", "Screens": "empty", "tomatoMeter": "96%", "popularity": "757", "contentrating": "R", "metascore": "76", "budget": "empty", "releasedate": "13 Feb 2015", "imdb_rating": "7.6", "rotten_url": "https://www.rottentomatoes.com/m/what_we_do_in_the_shadows/", "tomatoRating": "7.8", "year": "2014", "Genre": ["Comedy", "Fantasy", "Horror"], "userrating": "4.1", "runtime": "86 min", "OpeningWeekend": "empty"}, "tt3007512": {"userMeter": "61%", "userreviews": "13,246", "Gross": "$4,190,530", "title": "The Water Diviner", "url": "http://www.imdb.com/title/tt3007512/?ref_=nv_sr_1", "Screens": "320", "tomatoMeter": "63%", "popularity": "1,834", "contentrating": "R", "metascore": "50", "budget": "$22,500,000", "releasedate": "26 Dec 2014", "imdb_rating": "7.1", "rotten_url": "https://www.rottentomatoes.com/m/the_water_diviner/", "tomatoRating": "6", "year": "2014", "Genre": ["Drama", "War"], "userrating": "3.5", "runtime": "111 min", "OpeningWeekend": "$1,220,335 (USA) "}, "tt3612616": {"userMeter": "89%", "userreviews": "7,170", "Gross": "$3,492,754", "title": "Mommy", "url": "http://www.imdb.com/title/tt3612616/?ref_=nv_sr_1", "Screens": "4", "tomatoMeter": "89%", "popularity": "2,638", "contentrating": "R", "metascore": "74", "budget": "empty", "releasedate": "08 Oct 2014", "imdb_rating": "8.1", "rotten_url": "https://www.rottentomatoes.com/m/mommy_2015/", "tomatoRating": "7.9", "year": "2014", "Genre": ["Drama"], "userrating": "4.2", "runtime": "139 min", "OpeningWeekend": "$22,204 (USA) "}, "tt2234003": {"userMeter": "80%", "userreviews": "17,625", "Gross": "$3,541,350", "title": "Calvary", "url": "http://www.imdb.com/title/tt2234003/?ref_=nv_sr_1", "Screens": "4", "tomatoMeter": "89%", "popularity": "3,801", "contentrating": "R", "metascore": "77", "budget": "empty", "releasedate": "11 Apr 2014", "imdb_rating": "7.4", "rotten_url": "https://www.rottentomatoes.com/m/calvary_2013/", "tomatoRating": "7.6", "year": "2014", "Genre": ["Comedy", "Drama"], "userrating": "3.9", "runtime": "102 min", "OpeningWeekend": "$74,149 (USA) "}, "tt2908856": {"userMeter": "42%", "userreviews": "3,955", "Gross": "$1,474,563", "title": "My Old Lady", "url": "http://www.imdb.com/title/tt2908856/?ref_=nv_sr_1", "tomatoMeter": "60%", "popularity": "empty", "contentrating": "PG-13", "metascore": "52", "budget": "$5,000,000", "releasedate": "21 Nov 2014", "imdb_rating": "6.3", "rotten_url": "https://www.rottentomatoes.com/m/my_old_lady/", "tomatoRating": "5.8", "year": "2014", "Genre": ["Comedy", "Drama", "Romance"], "userrating": "3.1", "runtime": "107 min"}, "tt3062976": {"userMeter": "60%", "userreviews": "3,713", "Gross": "$3,446,820", "title": "Learning to Drive", "url": "http://www.imdb.com/title/tt3062976/?ref_=nv_sr_1", "Screens": "4", "tomatoMeter": "65%", "popularity": "empty", "contentrating": "R", "metascore": "59", "budget": "empty", "releasedate": "21 Aug 2015", "imdb_rating": "6.4", "rotten_url": "https://www.rottentomatoes.com/m/learning_to_drive/", "tomatoRating": "6.2", "year": "2014", "Genre": ["Comedy", "Drama", "Romance"], "userrating": "3.4", "runtime": "90 min", "OpeningWeekend": "$66,015 (USA) "}, "tt2870708": {"userMeter": "60%", "userreviews": "17,319", "Gross": "$3,588,432", "title": "Wish I Was Here", "url": "http://www.imdb.com/title/tt2870708/?ref_=nv_sr_1", "Screens": "68", "tomatoMeter": "44%", "popularity": "3,400", "contentrating": "R", "metascore": "43", "budget": "$6,000,000", "releasedate": "25 Jul 2014", "imdb_rating": "6.7", "rotten_url": "https://www.rottentomatoes.com/m/wish_i_was_here/", "tomatoRating": "5.3", "year": "2014", "Genre": ["Comedy", "Drama"], "userrating": "3.5", "runtime": "106 min", "OpeningWeekend": "$484,401 (USA) "}}