{"tt0450314": {"Gross": "7948159", "title": "Punisher: War Zone", "url": "http://www.imdb.com/title/tt0450314/?ref_=nv_sr_1", "releasedate": "05 Dec 2008", "popularity": "2488", "contentrating": "R", "metascore": "30", "budget": "35000000", "Screens": "2508", "imdb_rating": "6.0", "OpeningWeekend": "4271451", "year": "2008", "Genre": ["Action", "Crime", "Drama"], "runtime": "103 min"}, "tt0443274": {"Gross": "72266306", "title": "Vantage Point", "url": "http://www.imdb.com/title/tt0443274/?ref_=nv_sr_1", "releasedate": "22 Feb 2008", "popularity": "3621", "contentrating": "PG-13", "metascore": "40", "budget": "40000000", "Screens": "3149", "imdb_rating": "6.6", "OpeningWeekend": "22874936", "year": "2008", "Genre": ["Crime", "Drama", "Mystery"], "runtime": "90 min"}, "tt0880578": {"Gross": "28687835", "title": "Untraceable", "url": "http://www.imdb.com/title/tt0880578/?ref_=nv_sr_1", "releasedate": "25 Jan 2008", "popularity": "4388", "contentrating": "R", "metascore": "32", "budget": "35000000", "Screens": "2316", "imdb_rating": "6.2", "OpeningWeekend": "11354069", "year": "2008", "Genre": ["Crime", "Drama", "Thriller"], "runtime": "101 min"}, "tt0467197": {"Gross": "40689393", "title": "Max Payne", "url": "http://www.imdb.com/title/tt0467197/?ref_=nv_sr_1", "releasedate": "17 Oct 2008", "popularity": "3326", "contentrating": "PG-13", "metascore": "31", "budget": "35000000", "Screens": "empty", "imdb_rating": "5.4", "OpeningWeekend": "empty", "year": "2008", "Genre": ["Action", "Crime", "Drama"], "runtime": "100 min"}, "tt0910936": {"Gross": "87341380", "title": "Pineapple Express", "url": "http://www.imdb.com/title/tt0910936/?ref_=nv_sr_1", "releasedate": "06 Aug 2008", "popularity": "1119", "contentrating": "R", "metascore": "64", "budget": "27000000", "Screens": "3072", "imdb_rating": "7.0", "OpeningWeekend": "23245025", "year": "2008", "Genre": ["Action", "Comedy", "Crime"], "runtime": "111 min"}, "tt0814022": {"Gross": "15232982", "title": "Bangkok Dangerous", "url": "http://www.imdb.com/title/tt0814022/?ref_=nv_sr_1", "releasedate": "05 Sep 2008", "popularity": "empty", "contentrating": "R", "metascore": "24", "budget": "40000000", "Screens": "2650", "imdb_rating": "5.4", "OpeningWeekend": "7783266", "year": "2008", "Genre": ["Action", "Crime", "Thriller"], "runtime": "99 min"}, "tt0780536": {"Gross": "7757130", "title": "In Bruges", "url": "http://www.imdb.com/title/tt0780536/?ref_=nv_sr_1", "releasedate": "29 Feb 2008", "popularity": "1229", "contentrating": "R", "metascore": "67", "budget": "15000000", "Screens": "28", "imdb_rating": "8.0", "OpeningWeekend": "457227", "year": "2008", "Genre": ["Comedy", "Crime", "Drama"], "runtime": "107 min"}, "tt0951216": {"Gross": "20668843", "title": "Mad Money", "url": "http://www.imdb.com/title/tt0951216/?ref_=nv_sr_1", "releasedate": "18 Jan 2008", "popularity": "empty", "contentrating": "PG-13", "metascore": "41", "budget": "22000000", "Screens": "2470", "imdb_rating": "5.8", "OpeningWeekend": "9273645", "year": "2008", "Genre": ["Comedy", "Crime", "Thriller"], "runtime": "104 min"}, "tt0200465": {"Gross": "30028592", "title": "The Bank Job", "url": "http://www.imdb.com/title/tt0200465/?ref_=nv_sr_1", "releasedate": "07 Mar 2008", "popularity": "2385", "contentrating": "R", "metascore": "69", "budget": "20000000", "Screens": "1603", "imdb_rating": "7.3", "OpeningWeekend": "5935256", "year": "2008", "Genre": ["Crime", "Drama", "Romance"], "runtime": "111 min"}, "tt0486578": {"Gross": "37931869", "title": "First Sunday", "url": "http://www.imdb.com/title/tt0486578/?ref_=nv_sr_1", "releasedate": "11 Jan 2008", "popularity": "empty", "contentrating": "PG-13", "metascore": "41", "budget": "empty", "Screens": "2213", "imdb_rating": "4.3", "OpeningWeekend": "17714821", "year": "2008", "Genre": ["Comedy", "Crime", "Drama"], "runtime": "96 min"}, "tt0978759": {"Gross": "2508841", "title": "Frozen River", "url": "http://www.imdb.com/title/tt0978759/?ref_=nv_sr_1", "releasedate": "05 Sep 2008", "popularity": "empty", "contentrating": "R", "metascore": "82", "budget": "1000000", "Screens": "7", "imdb_rating": "7.2", "OpeningWeekend": "70234", "year": "2008", "Genre": ["Crime", "Drama"], "runtime": "97 min"}, "tt0478087": {"Gross": "81159365", "title": "21", "url": "http://www.imdb.com/title/tt0478087/?ref_=nv_sr_1", "releasedate": "28 Mar 2008", "popularity": "2033", "contentrating": "PG-13", "metascore": "48", "budget": "35000000", "Screens": "2648", "imdb_rating": "6.8", "OpeningWeekend": "24105943", "year": "2008", "Genre": ["Crime", "Drama", "Thriller"], "runtime": "123 min"}, "tt0988047": {"Gross": "23530831", "title": "Traitor", "url": "http://www.imdb.com/title/tt0988047/?ref_=nv_sr_1", "releasedate": "27 Aug 2008", "popularity": "empty", "contentrating": "PG-13", "metascore": "60", "budget": "22000000", "Screens": "2054", "imdb_rating": "7.0", "OpeningWeekend": "10006327", "year": "2008", "Genre": ["Action", "Crime", "Drama"], "runtime": "114 min"}, "tt1046997": {"Gross": "7916887", "title": "Miracle at St. Anna", "url": "http://www.imdb.com/title/tt1046997/?ref_=nv_sr_1", "releasedate": "26 Sep 2008", "popularity": "empty", "contentrating": "R", "metascore": "37", "budget": "45000000", "Screens": "1185", "imdb_rating": "6.0", "OpeningWeekend": "3477996", "year": "2008", "Genre": ["Action", "Crime", "Drama"], "runtime": "160 min"}, "tt0800308": {"Gross": "20207003", "title": "Appaloosa", "url": "http://www.imdb.com/title/tt0800308/?ref_=nv_sr_1", "releasedate": "03 Oct 2008", "popularity": "3491", "contentrating": "R", "metascore": "64", "budget": "empty", "Screens": "14", "imdb_rating": "6.8", "OpeningWeekend": "248847", "year": "2008", "Genre": ["Crime", "Drama", "Romance"], "runtime": "115 min"}, "tt0824747": {"Gross": "35707327", "title": "Changeling", "url": "http://www.imdb.com/title/tt0824747/?ref_=nv_sr_1", "releasedate": "31 Oct 2008", "popularity": "1929", "contentrating": "R", "metascore": "63", "budget": "55000000", "Screens": "1", "imdb_rating": "7.8", "OpeningWeekend": "9351560", "year": "2008", "Genre": ["Crime", "Drama", "Mystery"], "runtime": "141 min"}, "tt1032755": {"Gross": "5694401", "title": "RocknRolla", "url": "http://www.imdb.com/title/tt1032755/?ref_=nv_sr_1", "releasedate": "31 Oct 2008", "popularity": "1300", "contentrating": "R", "metascore": "53", "budget": "18000000", "Screens": "7", "imdb_rating": "7.3", "OpeningWeekend": "144701", "year": "2008", "Genre": ["Action", "Crime", "Thriller"], "runtime": "114 min"}, "tt0468569": {"Gross": "534858444", "title": "The Dark Knight", "url": "http://www.imdb.com/title/tt0468569/?ref_=nv_sr_1", "releasedate": "18 Jul 2008", "popularity": "89\n                </span", "contentrating": "PG-13", "metascore": "82", "budget": "185000000", "Screens": "4366", "imdb_rating": "9.0", "OpeningWeekend": "158411483", "year": "2008", "Genre": ["Action", "Crime", "Drama"], "runtime": "152 min"}, "tt0947802": {"Gross": "39263506", "title": "Lakeview Terrace", "url": "http://www.imdb.com/title/tt0947802/?ref_=nv_sr_1", "releasedate": "19 Sep 2008", "popularity": "empty", "contentrating": "PG-13", "metascore": "47", "budget": "22000000", "Screens": "2464", "imdb_rating": "6.1", "OpeningWeekend": "15004672", "year": "2008", "Genre": ["Crime", "Drama", "Thriller"], "runtime": "110 min"}, "tt1001562": {"Gross": "4131640", "title": "Witless Protection", "url": "http://www.imdb.com/title/tt1001562/?ref_=nv_sr_1", "releasedate": "22 Feb 2008", "popularity": "empty", "contentrating": "PG-13", "metascore": "17", "budget": "7500000", "Screens": "1333", "imdb_rating": "3.1", "OpeningWeekend": "2116692", "year": "2008", "Genre": ["Comedy", "Crime"], "runtime": "97 min"}, "tt1034331": {"Gross": "40076438", "title": "Righteous Kill", "url": "http://www.imdb.com/title/tt1034331/?ref_=nv_sr_1", "releasedate": "12 Sep 2008", "popularity": "4992", "contentrating": "R", "metascore": "36", "budget": "60000000", "Screens": "3152", "imdb_rating": "6.0", "OpeningWeekend": "16288361", "year": "2008", "Genre": ["Action", "Crime", "Drama"], "runtime": "101 min"}, "tt0800241": {"Gross": "2203641", "title": "Transsiberian", "url": "http://www.imdb.com/title/tt0800241/?ref_=nv_sr_1", "releasedate": "05 Sep 2008", "popularity": "empty", "contentrating": "R", "metascore": "72", "budget": "15000000", "Screens": "2", "imdb_rating": "6.7", "OpeningWeekend": "34615", "year": "2008", "Genre": ["Crime", "Drama", "Mystery"], "runtime": "111 min"}, "tt0800240": {"Gross": "4597760", "title": "Deception", "url": "http://www.imdb.com/title/tt0800240/?ref_=nv_sr_1", "releasedate": "25 Apr 2008", "popularity": "4169", "contentrating": "R", "metascore": "31", "budget": "25000000", "Screens": "2001", "imdb_rating": "6.1", "OpeningWeekend": "2312146", "year": "2008", "Genre": ["Crime", "Drama", "Mystery"], "runtime": "107 min"}, "tt0493464": {"Gross": "332816", "title": "Wanted", "url": "http://www.imdb.com/title/tt0493464/?ref_=nv_sr_1", "releasedate": "27 Jun 2008", "popularity": "1368", "contentrating": "R", "metascore": "64", "budget": "75000000", "Screens": "71", "imdb_rating": "6.7", "OpeningWeekend": "217432", "year": "2008", "Genre": ["Action", "Crime", "Fantasy"], "runtime": "110 min"}, "tt1129442": {"Gross": "31316973", "title": "Transporter 3", "url": "http://www.imdb.com/title/tt1129442/?ref_=nv_sr_1", "releasedate": "26 Nov 2008", "popularity": "3379", "contentrating": "PG-13", "metascore": "51", "budget": "30000000", "Screens": "2626", "imdb_rating": "6.1", "OpeningWeekend": "12063452", "year": "2008", "Genre": ["Action", "Adventure", "Crime"], "runtime": "104 min"}, "tt0448157": {"Gross": "227946274", "title": "Hancock", "url": "http://www.imdb.com/title/tt0448157/?ref_=nv_sr_1", "releasedate": "02 Jul 2008", "popularity": "1042", "contentrating": "PG-13", "metascore": "49", "budget": "150000000", "Screens": "3965", "imdb_rating": "6.4", "OpeningWeekend": "62603879", "year": "2008", "Genre": ["Action", "Crime", "Drama"], "runtime": "92 min"}, "tt0831887": {"Gross": "19781879", "title": "The Spirit", "url": "http://www.imdb.com/title/tt0831887/?ref_=nv_sr_1", "releasedate": "25 Dec 2008", "popularity": "3788", "contentrating": "PG-13", "metascore": "30", "budget": "60000000", "Screens": "2509", "imdb_rating": "4.8", "OpeningWeekend": "6463278", "year": "2008", "Genre": ["Action", "Crime", "Fantasy"], "runtime": "103 min"}, "tt0482572": {"Gross": "15709385", "title": "Pride and Glory", "url": "http://www.imdb.com/title/tt0482572/?ref_=nv_sr_1", "releasedate": "24 Oct 2008", "popularity": "3885", "contentrating": "R", "metascore": "45", "budget": "30000000", "Screens": "2585", "imdb_rating": "6.7", "OpeningWeekend": "6262396", "year": "2008", "Genre": ["Crime", "Drama", "Thriller"], "runtime": "130 min"}, "tt0421073": {"Gross": "26415649", "title": "Street Kings", "url": "http://www.imdb.com/title/tt0421073/?ref_=nv_sr_1", "releasedate": "11 Apr 2008", "popularity": "2590", "contentrating": "R", "metascore": "55", "budget": "20000000", "Screens": "2467", "imdb_rating": "6.8", "OpeningWeekend": "12469631", "year": "2008", "Genre": ["Action", "Crime", "Drama"], "runtime": "109 min"}}