{"tt0361089": {"Gross": "26273815", "title": "Valiant", "url": "http://www.imdb.com/title/tt0361089/?ref_=nv_sr_1", "releasedate": "19 Aug 2005", "popularity": "empty", "contentrating": "G", "metascore": "45", "budget": "47285491", "Screens": "2014", "imdb_rating": "5.6", "OpeningWeekend": "7990872", "year": "2005", "Genre": ["Animation", "Adventure", "Comedy"], "runtime": "76 min"}, "tt0339334": {"Gross": "10018917", "title": "Sprung! The Magic Roundabout", "url": "http://www.imdb.com/title/tt0339334/?ref_=nv_sr_1", "releasedate": "02 Feb 2005", "popularity": "empty", "contentrating": "N/A", "metascore": "N/A", "budget": "27020280", "Screens": "empty", "imdb_rating": "5.3", "OpeningWeekend": "empty", "year": "2005", "Genre": ["Animation", "Adventure", "Comedy"], "runtime": "85 min"}, "tt0371606": {"Gross": "182902316", "title": "Chicken Little", "url": "http://www.imdb.com/title/tt0371606/?ref_=nv_sr_1", "releasedate": "04 Nov 2005", "popularity": "3669", "contentrating": "G", "metascore": "48", "budget": "202652106", "Screens": "3654", "imdb_rating": "5.8", "OpeningWeekend": "54107812", "year": "2005", "Genre": ["Animation", "Adventure", "Comedy"], "runtime": "81 min"}, "tt0443536": {"Gross": "68974383", "title": "Hoodwinked!", "url": "http://www.imdb.com/title/tt0443536/?ref_=nv_sr_1", "releasedate": "13 Jan 2006", "popularity": "4663", "contentrating": "PG", "metascore": "45", "budget": "23642745", "Screens": "2394", "imdb_rating": "6.5", "OpeningWeekend": "22804309", "year": "2005", "Genre": ["Animation", "Action", "Comedy"], "runtime": "80 min"}, "tt0312004": {"Gross": "75749394", "title": "The Curse of the Were-Rabbit", "url": "http://www.imdb.com/title/tt0312004/?ref_=nv_sr_1", "releasedate": "07 Oct 2005", "popularity": "empty", "contentrating": "G", "metascore": "87", "budget": "40530421", "Screens": "3645", "imdb_rating": "7.5", "OpeningWeekend": "21651333", "year": "2005", "Genre": ["Animation", "Comedy", "Family"], "runtime": "85 min"}, "tt0121164": {"Gross": "72059857", "title": "Corpse Bride", "url": "http://www.imdb.com/title/tt0121164/?ref_=nv_sr_1", "releasedate": "23 Sep 2005", "popularity": "1638", "contentrating": "PG", "metascore": "83", "budget": "54040561", "Screens": "5", "imdb_rating": "7.4", "OpeningWeekend": "520245", "year": "2005", "Genre": ["Animation", "Drama", "Family"], "runtime": "77 min"}, "tt0351283": {"Gross": "260930419", "title": "Madagascar", "url": "http://www.imdb.com/title/tt0351283/?ref_=nv_sr_1", "releasedate": "27 May 2005", "popularity": "1988", "contentrating": "PG", "metascore": "57", "budget": "101326053", "Screens": "empty", "imdb_rating": "6.9", "OpeningWeekend": "empty", "year": "2005", "Genre": ["Animation", "Adventure", "Comedy"], "runtime": "86 min"}, "tt0401623": {"Gross": "46117591", "title": "Magnificent Desolation: Walking on the Moon 3D", "url": "http://www.imdb.com/title/tt0401623/?ref_=nv_sr_1", "releasedate": "23 Sep 2005", "popularity": "empty", "contentrating": "UNRATED", "metascore": "71", "budget": "empty", "Screens": "6", "imdb_rating": "7.0", "OpeningWeekend": "43054", "year": "2005", "Genre": ["Documentary", "Animation", "Short"], "runtime": "40 min"}, "tt0407121": {"Gross": "24428530", "title": "Pooh's Heffalump Movie", "url": "http://www.imdb.com/title/tt0407121/?ref_=nv_sr_1", "releasedate": "11 Feb 2005", "popularity": "empty", "contentrating": "G", "metascore": "64", "budget": "27020280", "Screens": "2529", "imdb_rating": "6.4", "OpeningWeekend": "7843391", "year": "2005", "Genre": ["Animation", "Family", "Fantasy"], "runtime": "68 min"}, "tt0358082": {"Gross": "173200016", "title": "Robots", "url": "http://www.imdb.com/title/tt0358082/?ref_=nv_sr_1", "releasedate": "11 Mar 2005", "popularity": "2960", "contentrating": "PG", "metascore": "64", "budget": "101326053", "Screens": "3776", "imdb_rating": "6.3", "OpeningWeekend": "48697707", "year": "2005", "Genre": ["Animation", "Adventure", "Comedy"], "runtime": "91 min"}}