{"tt0268575": {"userMeter": "empty", "userreviews": "4", "title": "Ride", "url": "http://www.imdb.com/title/tt0268575/?ref_=nv_sr_1", "releasedate": "08 Oct 2000", "Gross": "5103856", "popularity": "empty", "contentrating": "N/A", "metascore": "N/A", "budget": "empty", "Screens": "empty", "imdb_rating": "6.5", "rotten_url": "https://www.rottentomatoes.com/m/ride-2000/", "tomatoRating": "empty", "year": "2000", "Genre": ["Documentary", "Sport"], "userrating": "N", "runtime": "97 min", "tomatoMeter": "empty", "OpeningWeekend": "empty"}, "tt0217756": {"userMeter": "52", "userreviews": "33506", "Gross": "19878491", "url": "http://www.imdb.com/title/tt0217756/?ref_=nv_sr_1", "releasedate": "07 Apr 2000", "tomatoMeter": "23", "title": "Ready to Rumble", "contentrating": "PG-13", "metascore": "23", "popularity": "empty", "Screens": "2585", "imdb_rating": "5.3", "rotten_url": "https://www.rottentomatoes.com/m/ready_to_rumble/", "tomatoRating": "3.9", "userrating": "2.7", "year": "2000", "Genre": ["Comedy", "Sport"], "budget": "38560296", "runtime": "107 min", "OpeningWeekend": "8447561"}, "tt0196106": {"userMeter": "39", "userreviews": "7118", "Gross": "2002302", "url": "http://www.imdb.com/title/tt0196106/?ref_=nv_sr_1", "releasedate": "20 Oct 2000", "tomatoMeter": "20", "title": "MVP: Most Valuable Primate", "contentrating": "PG", "metascore": "43", "popularity": "empty", "Screens": "205", "imdb_rating": "3.8", "rotten_url": "https://www.rottentomatoes.com/m/mvp_most_valuable_primate/", "tomatoRating": "4.2", "userrating": "2.7", "year": "2000", "Genre": ["Comedy", "Family", "Sport"], "budget": "7230055", "runtime": "93 min", "OpeningWeekend": "325416"}, "tt0210945": {"userMeter": "93", "userreviews": "577424", "Gross": "185810156", "url": "http://www.imdb.com/title/tt0210945/?ref_=nv_sr_1", "releasedate": "29 Sep 2000", "tomatoMeter": "73", "title": "Remember the Titans", "contentrating": "PG", "metascore": "48", "popularity": "1014", "Screens": "1865", "imdb_rating": "7.8", "rotten_url": "https://www.rottentomatoes.com/m/remember_the_titans/", "tomatoRating": "6.3", "userrating": "3.9", "year": "2000", "Genre": ["Biography", "Drama", "Sport"], "budget": "48200371", "runtime": "113 min", "OpeningWeekend": "33588960"}, "tt0188160": {"userMeter": "76", "userreviews": "1375", "Gross": "5518163", "url": "http://www.imdb.com/title/tt0188160/?ref_=nv_sr_1", "releasedate": "31 Mar 2000", "tomatoMeter": "33", "title": "Price of Glory", "contentrating": "PG-13", "metascore": "32", "popularity": "empty", "Screens": "802", "imdb_rating": "6.5", "rotten_url": "https://www.rottentomatoes.com/m/price_of_glory/", "tomatoRating": "4.8", "userrating": "3.8", "year": "2000", "Genre": ["Drama", "Sport"], "budget": "28920222", "runtime": "118 min", "OpeningWeekend": "2589698"}, "tt0191397": {"userMeter": "66", "userreviews": "159528", "Gross": "71878094", "url": "http://www.imdb.com/title/tt0191397/?ref_=nv_sr_1", "releasedate": "11 Aug 2000", "tomatoMeter": "41", "title": "The Replacements", "contentrating": "PG-13", "metascore": "30", "popularity": "2622", "Screens": "2754", "imdb_rating": "6.5", "rotten_url": "https://www.rottentomatoes.com/m/replacements/", "tomatoRating": "5", "userrating": "3.1", "year": "2000", "Genre": ["Comedy", "Sport"], "budget": "80333951", "runtime": "118 min", "OpeningWeekend": "17736473"}, "tt0204946": {"userMeter": "66", "userreviews": "767274", "Gross": "109863105", "url": "http://www.imdb.com/title/tt0204946/?ref_=nv_sr_1", "releasedate": "25 Aug 2000", "tomatoMeter": "63", "title": "Bring It On", "contentrating": "PG-13", "metascore": "52", "popularity": "1225", "Screens": "2380", "imdb_rating": "5.9", "rotten_url": "https://www.rottentomatoes.com/m/bring_it_on/", "tomatoRating": "5.9", "userrating": "3.1", "year": "2000", "Genre": ["Comedy", "Sport"], "budget": "44987012", "runtime": "98 min", "OpeningWeekend": "27895330"}, "tt0199725": {"userMeter": "95", "userreviews": "186481", "Gross": "44089075", "url": "http://www.imdb.com/title/tt0199725/?ref_=nv_sr_1", "releasedate": "21 Apr 2000", "tomatoMeter": "82", "title": "Love & Basketball", "contentrating": "PG-13", "metascore": "70", "popularity": "4835", "Screens": "1237", "imdb_rating": "7.2", "rotten_url": "https://www.rottentomatoes.com/m/love_and_basketball/", "tomatoRating": "6.7", "userrating": "3.9", "year": "2000", "Genre": ["Drama", "Romance", "Sport"], "budget": "32133580", "runtime": "124 min", "OpeningWeekend": "13077049"}, "tt0156812": {"userMeter": "67", "userreviews": "46307", "Gross": "54787176", "url": "http://www.imdb.com/title/tt0156812/?ref_=nv_sr_1", "releasedate": "03 Mar 2000", "tomatoMeter": "73", "title": "My Dog Skip", "contentrating": "PG", "metascore": "61", "popularity": "empty", "Screens": "5", "imdb_rating": "7.0", "rotten_url": "https://www.rottentomatoes.com/m/my_dog_skip/", "tomatoRating": "6.7", "userrating": "3.1", "year": "2000", "Genre": ["Drama", "Family", "Sport"], "budget": "9640074", "runtime": "95 min", "OpeningWeekend": "91485"}, "tt0245280": {"userMeter": "82", "userreviews": "3118", "Gross": "29952221", "url": "http://www.imdb.com/title/tt0245280/?ref_=nv_sr_1", "releasedate": "05 May 2000", "tomatoMeter": "67", "title": "Michael Jordan to the Max", "contentrating": "N/A", "metascore": "57", "popularity": "empty", "Screens": "41", "imdb_rating": "7.5", "rotten_url": "https://www.rottentomatoes.com/m/michael-jordan-to-the-max/", "tomatoRating": "6.2", "userrating": "3.8", "year": "2000", "Genre": ["Documentary", "Sport"], "budget": "empty", "runtime": "46 min", "OpeningWeekend": "928887"}, "tt0146984": {"userMeter": "65", "userreviews": "50914", "Gross": "49317377", "url": "http://www.imdb.com/title/tt0146984/?ref_=nv_sr_1", "releasedate": "03 Nov 2000", "tomatoMeter": "43", "title": "The Legend of Bagger Vance", "contentrating": "PG-13", "metascore": "47", "popularity": "2686", "Screens": "2061", "imdb_rating": "6.7", "rotten_url": "https://www.rottentomatoes.com/m/legend_of_bagger_vance/", "tomatoRating": "5.2", "userrating": "3.2", "year": "2000", "Genre": ["Drama", "Fantasy", "Sport"], "budget": "128534322", "runtime": "126 min", "OpeningWeekend": "18503659"}, "tt0210075": {"userMeter": "74", "userreviews": "11782", "Gross": "2448484", "url": "http://www.imdb.com/title/tt0210075/?ref_=nv_sr_1", "releasedate": "06 Oct 2000", "tomatoMeter": "87", "title": "Girlfight", "contentrating": "R", "metascore": "70", "popularity": "empty", "Screens": "28", "imdb_rating": "6.8", "rotten_url": "https://www.rottentomatoes.com/m/girlfight/", "tomatoRating": "7.3", "userrating": "3.5", "year": "2000", "Genre": ["Drama", "Sport"], "budget": "1606679", "runtime": "110 min", "OpeningWeekend": "317955"}}