{"tt0363771": {"userMeter": "61", "userreviews": "34104134", "Gross": "394104096", "url": "http://www.imdb.com/title/tt0363771/?ref_=nv_sr_1", "releasedate": "09 Dec 2005", "tomatoMeter": "76", "title": "The Chronicles of Narnia: The Lion, the Witch and the Wardrobe", "contentrating": "PG", "metascore": "75", "popularity": "423", "Screens": "empty", "imdb_rating": "6.9", "rotten_url": "https://www.rottentomatoes.com/m/chronicles_of_narnia_lion_witch_wardrobe/", "tomatoRating": "6.9", "userrating": "3.1", "year": "2005", "Genre": ["Adventure", "Family", "Fantasy"], "budget": "243182527", "runtime": "143 min", "OpeningWeekend": "88567497"}, "tt0362165": {"userMeter": "15", "userreviews": "38515", "Gross": "22981621", "url": "http://www.imdb.com/title/tt0362165/?ref_=nv_sr_1", "releasedate": "18 Feb 2005", "tomatoMeter": "6", "title": "Son of the Mask", "contentrating": "PG", "metascore": "20", "popularity": "4684", "Screens": "2966", "imdb_rating": "2.2", "rotten_url": "https://www.rottentomatoes.com/m/son_of_the_mask/", "tomatoRating": "2.8", "userrating": "2.0", "year": "2005", "Genre": ["Comedy", "Family", "Fantasy"], "budget": "113485179", "runtime": "94 min", "OpeningWeekend": "10148378"}, "tt0443295": {"userMeter": "51", "userreviews": "397948", "Gross": "72161526", "url": "http://www.imdb.com/title/tt0443295/?ref_=nv_sr_1", "releasedate": "23 Nov 2005", "tomatoMeter": "6", "title": "Yours, Mine & Ours", "contentrating": "PG", "metascore": "38", "popularity": "3008", "Screens": "empty", "imdb_rating": "5.4", "rotten_url": "https://www.rottentomatoes.com/m/yours_mine_and_ours/", "tomatoRating": "3.3", "userrating": "3.2", "year": "2005", "Genre": ["Comedy", "Family", "Fantasy"], "budget": "60795631", "runtime": "88 min", "OpeningWeekend": "23590202"}, "tt0330373": {"userMeter": "74", "userreviews": "34151239", "Gross": "391811683", "url": "http://www.imdb.com/title/tt0330373/?ref_=nv_sr_1", "releasedate": "18 Nov 2005", "tomatoMeter": "88", "title": "Harry Potter and the Goblet of Fire", "contentrating": "PG-13", "metascore": "81", "popularity": "161", "Screens": "3858", "imdb_rating": "7.7", "rotten_url": "https://www.rottentomatoes.com/m/harry_potter_and_the_goblet_of_fire/", "tomatoRating": "7.5", "userrating": "3.4", "year": "2005", "Genre": ["Adventure", "Family", "Fantasy"], "budget": "202652106", "runtime": "157 min", "OpeningWeekend": "138256111"}, "tt0396752": {"userMeter": "63", "userreviews": "494860", "Gross": "63692354", "url": "http://www.imdb.com/title/tt0396752/?ref_=nv_sr_1", "releasedate": "27 Jan 2006", "tomatoMeter": "73", "title": "Nanny McPhee", "contentrating": "PG", "metascore": "59", "popularity": "2247", "Screens": "1995", "imdb_rating": "6.6", "rotten_url": "https://www.rottentomatoes.com/m/1153987-nanny_mcphee/", "tomatoRating": "6.6", "userrating": "3.2", "year": "2005", "Genre": ["Comedy", "Family", "Fantasy"], "budget": "33775351", "runtime": "97 min", "OpeningWeekend": "19594634"}, "tt0383222": {"userMeter": "16", "userreviews": "136026", "Gross": "3249756", "url": "http://www.imdb.com/title/tt0383222/?ref_=nv_sr_1", "releasedate": "06 Jan 2006", "tomatoMeter": "4", "title": "BloodRayne", "contentrating": "R", "metascore": "18", "popularity": "4063", "Screens": "985", "imdb_rating": "2.9", "rotten_url": "https://www.rottentomatoes.com/m/bloodrayne/", "tomatoRating": "2.3", "userrating": "2.5", "year": "2005", "Genre": ["Action", "Adventure", "Fantasy"], "budget": "33775351", "runtime": "95 min", "OpeningWeekend": "2094071"}, "tt0425123": {"userMeter": "75", "userreviews": "541219", "Gross": "65278472", "url": "http://www.imdb.com/title/tt0425123/?ref_=nv_sr_1", "releasedate": "16 Sep 2005", "tomatoMeter": "56", "title": "Just Like Heaven", "contentrating": "PG-13", "metascore": "47", "popularity": "4159", "Screens": "3508", "imdb_rating": "6.7", "rotten_url": "https://www.rottentomatoes.com/m/just_like_heaven/", "tomatoRating": "5.7", "userrating": "3.6", "year": "2005", "Genre": ["Comedy", "Fantasy", "Romance"], "budget": "78358814", "runtime": "95 min", "OpeningWeekend": "22168408"}, "tt0360486": {"userMeter": "72", "userreviews": "467293", "Gross": "102644883", "url": "http://www.imdb.com/title/tt0360486/?ref_=nv_sr_1", "releasedate": "18 Feb 2005", "tomatoMeter": "46", "title": "Constantine", "contentrating": "R", "metascore": "50", "popularity": "1084", "Screens": "3006", "imdb_rating": "6.9", "rotten_url": "https://www.rottentomatoes.com/m/constantine/", "tomatoRating": "5.5", "userrating": "3.5", "year": "2005", "Genre": ["Drama", "Fantasy", "Horror"], "budget": "135101404", "runtime": "121 min", "OpeningWeekend": "40218469"}, "tt0121766": {"userMeter": "65", "userreviews": "33676683", "Gross": "513740050", "url": "http://www.imdb.com/title/tt0121766/?ref_=nv_sr_1", "releasedate": "19 May 2005", "tomatoMeter": "79", "title": "Star Wars: Episode III - Revenge of the Sith", "contentrating": "PG-13", "metascore": "68", "popularity": "785", "Screens": "3661", "imdb_rating": "7.6", "rotten_url": "https://www.rottentomatoes.com/m/star_wars_episode_iii_revenge_of_the_sith", "tomatoRating": "7.3", "userrating": "3.1", "year": "2005", "Genre": ["Action", "Adventure", "Fantasy"], "budget": "152664586", "runtime": "140 min", "OpeningWeekend": "146498343"}, "tt0357277": {"userMeter": "30", "userreviews": "256954", "Gross": "32975475", "url": "http://www.imdb.com/title/tt0357277/?ref_=nv_sr_1", "releasedate": "14 Jan 2005", "tomatoMeter": "10", "title": "Elektra", "contentrating": "PG-13", "metascore": "34", "popularity": "3764", "Screens": "3203", "imdb_rating": "4.8", "rotten_url": "https://www.rottentomatoes.com/m/elektra/", "tomatoRating": "3.8", "userrating": "2.6", "year": "2005", "Genre": ["Action", "Crime", "Fantasy"], "budget": "58093603", "runtime": "97 min", "OpeningWeekend": "19984652"}, "tt0374536": {"userMeter": "28", "userreviews": "215239", "Gross": "84103886", "url": "http://www.imdb.com/title/tt0374536/?ref_=nv_sr_1", "releasedate": "24 Jun 2005", "tomatoMeter": "25", "title": "Bewitched", "contentrating": "PG-13", "metascore": "34", "popularity": "empty", "Screens": "3174", "imdb_rating": "4.8", "rotten_url": "https://www.rottentomatoes.com/m/bewitched/", "tomatoRating": "4.6", "userrating": "2.5", "year": "2005", "Genre": ["Comedy", "Fantasy", "Romance"], "budget": "114836193", "runtime": "102 min", "OpeningWeekend": "27197439"}, "tt0407121": {"userMeter": "69", "userreviews": "12926", "Gross": "24428530", "url": "http://www.imdb.com/title/tt0407121/?ref_=nv_sr_1", "releasedate": "11 Feb 2005", "tomatoMeter": "79", "title": "Pooh's Heffalump Movie", "contentrating": "G", "metascore": "64", "popularity": "empty", "Screens": "2529", "imdb_rating": "6.4", "rotten_url": "https://www.rottentomatoes.com/m/poohs_heffalump_movie/", "tomatoRating": "6.6", "userrating": "3.5", "year": "2005", "Genre": ["Animation", "Family", "Fantasy"], "budget": "27020280", "runtime": "68 min", "OpeningWeekend": "7843391"}}