{"tt0893382": {"Gross": "6459269", "title": "Shine a Light", "url": "http://www.imdb.com/title/tt0893382/?ref_=nv_sr_1", "releasedate": "04 Apr 2008", "popularity": "empty", "contentrating": "PG-13", "metascore": "76", "budget": "empty", "Screens": "276", "imdb_rating": "7.2", "OpeningWeekend": "1794816", "year": "2008", "Genre": ["Documentary", "Biography", "Music"], "runtime": "122 min"}, "tt1042877": {"Gross": "9810907", "title": "Cadillac Records", "url": "http://www.imdb.com/title/tt1042877/?ref_=nv_sr_1", "releasedate": "05 Dec 2008", "popularity": "3762", "contentrating": "R", "metascore": "65", "budget": "14473537", "Screens": "687", "imdb_rating": "7.0", "OpeningWeekend": "4155785", "year": "2008", "Genre": ["Biography", "Drama", "Music"], "runtime": "109 min"}, "tt0449994": {"Gross": "4149946", "title": "Jodhaa Akbar", "url": "http://www.imdb.com/title/tt0449994/?ref_=nv_sr_1", "releasedate": "15 Feb 2008", "popularity": "empty", "contentrating": "N/A", "metascore": "69", "budget": "7236768", "Screens": "100", "imdb_rating": "7.6", "OpeningWeekend": "1932646", "year": "2008", "Genre": ["Action", "Adventure", "Biography"], "runtime": "213 min"}, "tt0455538": {"Gross": "3351530", "title": "How to Lose Friends & Alienate People", "url": "http://www.imdb.com/title/tt0455538/?ref_=nv_sr_1", "releasedate": "03 Oct 2008", "popularity": "empty", "contentrating": "R", "metascore": "35", "budget": "32565459", "Screens": "1750", "imdb_rating": "6.5", "OpeningWeekend": "1725117", "year": "2008", "Genre": ["Biography", "Comedy", "Drama"], "runtime": "110 min"}, "tt1185616": {"Gross": "2753923", "title": "Waltz with Bashir", "url": "http://www.imdb.com/title/tt1185616/?ref_=nv_sr_1", "releasedate": "12 Jun 2008", "popularity": "empty", "contentrating": "R", "metascore": "91", "budget": "1809192", "Screens": "5", "imdb_rating": "8.0", "OpeningWeekend": "83289", "year": "2008", "Genre": ["Documentary", "Animation", "Biography"], "runtime": "90 min"}, "tt1054588": {"Gross": "4516696", "title": "Flash of Genius", "url": "http://www.imdb.com/title/tt1054588/?ref_=nv_sr_1", "releasedate": "03 Oct 2008", "popularity": "empty", "contentrating": "PG-13", "metascore": "57", "budget": "24122562", "Screens": "1098", "imdb_rating": "7.0", "OpeningWeekend": "2715084", "year": "2008", "Genre": ["Biography", "Drama"], "runtime": "119 min"}, "tt0467200": {"Gross": "32342274", "title": "The Other Boleyn Girl", "url": "http://www.imdb.com/title/tt0467200/?ref_=nv_sr_1", "releasedate": "29 Feb 2008", "popularity": "2108", "contentrating": "PG-13", "metascore": "50", "budget": "42214484", "Screens": "1166", "imdb_rating": "6.7", "OpeningWeekend": "9893942", "year": "2008", "Genre": ["Biography", "Drama", "History"], "runtime": "115 min"}, "tt1175491": {"Gross": "30797870", "title": "W.", "url": "http://www.imdb.com/title/tt1175491/?ref_=nv_sr_1", "releasedate": "17 Oct 2008", "popularity": "3813", "contentrating": "PG-13", "metascore": "56", "budget": "30273816", "Screens": "2030", "imdb_rating": "6.4", "OpeningWeekend": "12671181", "year": "2008", "Genre": ["Biography", "Drama", "History"], "runtime": "129 min"}, "tt0864761": {"Gross": "16673202", "title": "The Duchess", "url": "http://www.imdb.com/title/tt0864761/?ref_=nv_sr_1", "releasedate": "10 Oct 2008", "popularity": "3160", "contentrating": "PG-13", "metascore": "62", "budget": "21656030", "Screens": "7", "imdb_rating": "6.9", "OpeningWeekend": "229678", "year": "2008", "Genre": ["Biography", "Drama", "History"], "runtime": "110 min"}, "tt1013753": {"Gross": "38404686", "title": "Milk", "url": "http://www.imdb.com/title/tt1013753/?ref_=nv_sr_1", "releasedate": "30 Jan 2009", "popularity": "2424", "contentrating": "R", "metascore": "84", "budget": "24122562", "Screens": "882", "imdb_rating": "7.6", "OpeningWeekend": "1786462", "year": "2008", "Genre": ["Biography", "Drama", "History"], "runtime": "128 min"}, "tt1091751": {"Gross": "13880632", "title": "The Longshots", "url": "http://www.imdb.com/title/tt1091751/?ref_=nv_sr_1", "releasedate": "22 Aug 2008", "popularity": "empty", "contentrating": "PG", "metascore": "52", "budget": "27740947", "Screens": "empty", "imdb_rating": "5.1", "OpeningWeekend": "empty", "year": "2008", "Genre": ["Biography", "Comedy", "Drama"], "runtime": "94 min"}, "tt0469903": {"Gross": "11566618", "title": "The Express", "url": "http://www.imdb.com/title/tt0469903/?ref_=nv_sr_1", "releasedate": "10 Oct 2008", "popularity": "empty", "contentrating": "PG", "metascore": "58", "budget": "48245125", "Screens": "2808", "imdb_rating": "7.3", "OpeningWeekend": "5503170", "year": "2008", "Genre": ["Biography", "Drama", "Sport"], "runtime": "130 min"}}