{"tt0414853": {"Screens": "3,311", "title": "Barnyard", "url": "http://www.imdb.com/title/tt0414853/?ref_=nv_sr_1", "Gross": "$72,601,713", "popularity": "empty", "contentrating": "PG", "metascore": "42", "budget": "$51,000,000", "releasedate": "04 Aug 2006", "imdb_rating": "5.6", "OpeningWeekend": "$15,820,864 (USA) ", "year": "2006", "Genre": ["Animation", "Comedy", "Family"], "runtime": "90 min"}, "tt0385880": {"Screens": "3,553", "title": "Monster House", "url": "http://www.imdb.com/title/tt0385880/?ref_=nv_sr_1", "Gross": "$73,661,010", "popularity": "3,087", "contentrating": "PG", "metascore": "68", "budget": "$75,000,000", "releasedate": "21 Jul 2006", "imdb_rating": "6.6", "OpeningWeekend": "$22,217,226 (USA) ", "year": "2006", "Genre": ["Animation", "Comedy", "Family"], "runtime": "91 min"}, "tt0493430": {"Screens": "3,059", "title": "Jackass Number Two", "url": "http://www.imdb.com/title/tt0493430/?ref_=nv_sr_1", "Gross": "$18,755,517", "popularity": "empty", "contentrating": "R", "metascore": "66", "budget": "empty", "releasedate": "22 Sep 2006", "imdb_rating": "7.1", "OpeningWeekend": "$29,002,002 (USA) ", "year": "2006", "Genre": ["Documentary", "Action", "Comedy"], "runtime": "92 min"}, "tt0449010": {"Screens": "3,020", "title": "Eragon", "url": "http://www.imdb.com/title/tt0449010/?ref_=nv_sr_1", "Gross": "$75,021,527", "popularity": "1,787", "contentrating": "PG", "metascore": "38", "budget": "$100,000,000", "releasedate": "15 Dec 2006", "imdb_rating": "5.1", "OpeningWeekend": "$23,239,907 (USA) ", "year": "2006", "Genre": ["Action", "Adventure", "Family"], "runtime": "104 min"}, "tt0469641": {"Screens": "", "title": "World Trade Center", "url": "http://www.imdb.com/title/tt0469641/?ref_=nv_sr_1", "Gross": "$70,236,496", "popularity": "1,665", "contentrating": "PG-13", "metascore": "66", "budget": "$63,000,000", "releasedate": "09 Aug 2006", "imdb_rating": "6.0", "OpeningWeekend": "$18,730,762 (USA) ", "year": "2006", "Genre": ["Drama", "History", "Thriller"], "runtime": "129 min"}, "tt0479143": {"Screens": "", "title": "Rocky Balboa", "url": "http://www.imdb.com/title/tt0479143/?ref_=nv_sr_1", "Gross": "$70,261,813", "popularity": "1,253", "contentrating": "PG", "metascore": "63", "budget": "$24,000,000", "releasedate": "20 Dec 2006", "imdb_rating": "7.2", "OpeningWeekend": "$17,003,904 (USA) ", "year": "2006", "Genre": ["Drama", "Sport"], "runtime": "102 min"}, "tt0463034": {"Screens": "3,131", "title": "You, Me and Dupree", "url": "http://www.imdb.com/title/tt0463034/?ref_=nv_sr_1", "Gross": "$75,628,110", "popularity": "empty", "contentrating": "PG-13", "metascore": "46", "budget": "$54,000,000", "releasedate": "14 Jul 2006", "imdb_rating": "5.6", "OpeningWeekend": "$21,525,560 (USA) ", "year": "2006", "Genre": ["Comedy", "Romance"], "runtime": "110 min"}, "tt0421729": {"Screens": "3,261", "title": "Big Momma's House 2", "url": "http://www.imdb.com/title/tt0421729/?ref_=nv_sr_1", "Gross": "$70,163,652", "popularity": "empty", "contentrating": "PG-13", "metascore": "34", "budget": "$40,000,000", "releasedate": "27 Jan 2006", "imdb_rating": "4.6", "OpeningWeekend": "$27,736,056 (USA) ", "year": "2006", "Genre": ["Comedy", "Crime"], "runtime": "99 min"}, "tt0449089": {"Screens": "3,639", "title": "RV", "url": "http://www.imdb.com/title/tt0449089/?ref_=nv_sr_1", "Gross": "$71,402,035", "popularity": "3,489", "contentrating": "PG", "metascore": "33", "budget": "$65,000,000", "releasedate": "28 Apr 2006", "imdb_rating": "5.5", "OpeningWeekend": "$16,414,767 (USA) ", "year": "2006", "Genre": ["Adventure", "Comedy", "Family"], "runtime": "99 min"}, "tt0462590": {"Screens": "2", "title": "Step Up", "url": "http://www.imdb.com/title/tt0462590/?ref_=nv_sr_1", "Gross": "$65,328,121", "popularity": "1,293", "contentrating": "PG-13", "metascore": "48", "budget": "$12,000,000", "releasedate": "11 Aug 2006", "imdb_rating": "6.5", "OpeningWeekend": "$20,659,573 (USA) ", "year": "2006", "Genre": ["Crime", "Drama", "Music"], "runtime": "104 min"}}